pyrawr.py
pyrawr-0.1.0.dist-info/LICENSE
pyrawr-0.1.0.dist-info/WHEEL
pyrawr-0.1.0.dist-info/METADATA
pyrawr-0.1.0.dist-info/RECORD
