Metadata-Version: 2.1
Name: pyrawr
Version: 0.1.0
Summary: Python wrapper around the ThermoRawFileParser command line interface
Home-page: https://github.com/ralfg/pyrawr
License: Apache-2.0
Keywords: ThermoRawFileParser,mass spectrometry,proteomics,raw
Author: Ralf Gabriels
Author-email: ralf@gabriels.dev
Requires-Python: >=3.7,<4.0
Classifier: License :: OSI Approved :: Apache Software License
Classifier: Programming Language :: Python :: 3
Classifier: Programming Language :: Python :: 3.7
Classifier: Programming Language :: Python :: 3.8
Classifier: Programming Language :: Python :: 3.9
Requires-Dist: semver (>=2)
Project-URL: Documentation, https://pyrawr.readthedocs.io/
Project-URL: Repository, https://github.com/ralfg/pyrawr
